{
  "statusCode": 200,
  "body": "[{\"goal_2\": \"Motivation\", \"goal_1\": \"Overall Mood\", \"goal_5\": \"Do night exercises\", \"SK\": \"GOALS\", \"goal_4\": \"Stop snacking\", \"goal_3\": \"Do AWS/Python course work\", \"PK\": \"User#Darren_Fawcett\"}, {\"total_lost\": 0.7, \"current_week_numbers\": \"{\\\\\\\"SK\\\\\\\": \\\\\\\"LOG#2025-05-19\\\\\\\", \\\\\\\"week_weight\\\\\\\": 16.13, \\\\\\\"scores\\\\\\\": {\\\\\\\"goal_1\\\\\\\": 77.1, \\\\\\\"goal_3\\\\\\\": 77.1, \\\\\\\"total_score\\\\\\\": 80.6, \\\\\\\"goal_2\\\\\\\": 80.0, \\\\\\\"goal_5\\\\\\\": 88.6, \\\\\\\"goal_4\\\\\\\": 8.1}}\", \"current_week\": 16.3, \"SK\": \"DATA_UI\", \"high_score\": {\"score_%\": 81.6, \"score_date\": \"2025-05-26\"}, \"last_5_average_%\": 8.2, \"last_weeks_weight\": 16.2, \"7_day_lost\": 0.8, \"PK\": \"User#Darren_Fawcett\", \"last_weeks_numbers\": \"{\\\\\\\"SK\\\\\\\": \\\\\\\"LOG#2025-05-12\\\\\\\", \\\\\\\"week_weight\\\\\\\": 17.7, \\\\\\\"scores\\\\\\\": {\\\\\\\"goal_1\\\\\\\": 77.4, \\\\\\\"goal_3\\\\\\\": 77.1, \\\\\\\"total_score\\\\\\\": 80.6, \\\\\\\"goal_2\\\\\\\": 77.1, \\\\\\\"goal_5\\\\\\\": 100.0, \\\\\\\"goal_4\\\\\\\": 77.1}}\"}, {\"SK\": \"PROFILE\", \"PK\": \"User#Darren_Fawcett\", \"name\": \"Darren Fawcett\", \"start_weight\": 17.7, \"age\": 44.0, \"weigh_day\": \"Monday\"}]"
}